webdataset/__init__.py
webdataset/autodecode.py
webdataset/bench.py
webdataset/cache.py
webdataset/cborsiterators.py
webdataset/compat.py
webdataset/extradatasets.py
webdataset/filters.py
webdataset/gopen.py
webdataset/handlers.py
webdataset/mix.py
webdataset/multi.py
webdataset/pipeline.py
webdataset/pytorch.py
webdataset/shardlists.py
webdataset/tariterators.py
webdataset/tenbin.py
webdataset/utils.py
webdataset/writer.py
webdataset_py36-0.2.4.dist-info/LICENSE
webdataset_py36-0.2.4.dist-info/METADATA
webdataset_py36-0.2.4.dist-info/WHEEL
webdataset_py36-0.2.4.dist-info/top_level.txt
webdataset_py36-0.2.4.dist-info/RECORD
