Metadata-Version: 2.1
Name: webdataset-py36
Version: 0.2.4
Summary: Record sequential storage for deep learning.
Home-page: http://github.com/reuben/webdataset
Author: Reuben Morais
Author-email: reuben@github.account
License: MIT
Keywords: object store,client,deep learning
Platform: UNKNOWN
Classifier: Development Status :: 3 - Alpha
Classifier: License :: OSI Approved :: BSD License
Classifier: Programming Language :: Python :: 3.6
Classifier: Programming Language :: Python :: 3.7
Classifier: Programming Language :: Python :: 3.8
Classifier: Programming Language :: Python :: 3.9
Requires-Python: >=3.6
License-File: LICENSE
Requires-Dist: braceexpand
Requires-Dist: numpy
Requires-Dist: pyyaml
